hw1_forexAPI_library/__init__.py
hw1_forexAPI_library/forex_api.py
Forex_API_hw2-0.1.0.dist-info/METADATA
Forex_API_hw2-0.1.0.dist-info/WHEEL
Forex_API_hw2-0.1.0.dist-info/top_level.txt
Forex_API_hw2-0.1.0.dist-info/RECORD
